mgnn/__init__.py
mgnn/config.py
mgnn/dataloader/__init__.py
mgnn/dataloader/dataset.py
mgnn/graph/__init__.py
mgnn/graph/compute.py
mgnn/graph/converters.py
mgnn/layers/__init__.py
mgnn/layers/atom_ref.py
mgnn/layers/bond_expansion.py
mgnn/layers/core.py
mgnn/layers/cutoff_functions.py
mgnn/layers/embedding_block.py
mgnn/layers/graph_conv.py
mgnn/layers/readout_block.py
mgnn/layers/three_body.py
mgnn/models/__init__.py
mgnn/models/layers.py
mgnn/models/m3gnet.py
mgnn/models/megnet.py
mgnn/models/potential.py
mgnn/nbody/__init__.py
mgnn/nbody/three_body.py
mgnn/utils/__init__.py
mgnn/utils/maths.py
mgnn/utils/sb_roots.npy
mgnn-0.1.0.dev0.dist-info/LICENSE
mgnn-0.1.0.dev0.dist-info/METADATA
mgnn-0.1.0.dev0.dist-info/WHEEL
mgnn-0.1.0.dev0.dist-info/top_level.txt
mgnn-0.1.0.dev0.dist-info/RECORD
